LICENSE
srtools/LICENSE
srtools/__init__.py
srtools/_version.py
srtools/character_dictionaries.py
srtools/cli.py
srtools/transliteration.py
srtools-0.1.13.dist-info/entry_points.txt
srtools-0.1.13.dist-info/LICENSE
srtools-0.1.13.dist-info/WHEEL
srtools-0.1.13.dist-info/METADATA
srtools-0.1.13.dist-info/RECORD
